hdx_cli/__init__.py
hdx_cli/auth/__init__.py
hdx_cli/auth/api.py
hdx_cli/auth/auth.py
hdx_cli/auth/context_builder.py
hdx_cli/auth/service_account.py
hdx_cli/auth/session.py
hdx_cli/auth/utils.py
hdx_cli/cli_interface/__init__.py
hdx_cli/cli_interface/check_health/__init__.py
hdx_cli/cli_interface/check_health/cleaner/__init__.py
hdx_cli/cli_interface/check_health/cleaner/columns.py
hdx_cli/cli_interface/check_health/cleaner/elements.py
hdx_cli/cli_interface/check_health/cleaner/schemas.py
hdx_cli/cli_interface/check_health/cleaner/table.py
hdx_cli/cli_interface/check_health/cleaner/transform_columns.py
hdx_cli/cli_interface/check_health/cleaner/transforms.py
hdx_cli/cli_interface/check_health/cleaner/view_columns.py
hdx_cli/cli_interface/check_health/cleaner/views.py
hdx_cli/cli_interface/check_health/commands.py
hdx_cli/cli_interface/check_health/const.py
hdx_cli/cli_interface/check_health/reportlog.py
hdx_cli/cli_interface/check_health/utils.py
hdx_cli/cli_interface/column/commands.py
hdx_cli/cli_interface/common/__init__.py
hdx_cli/cli_interface/common/cached_operations.py
hdx_cli/cli_interface/common/click_extensions.py
hdx_cli/cli_interface/common/migration/__init__.py
hdx_cli/cli_interface/common/migration/logs.py
hdx_cli/cli_interface/common/migration/migration_rollback.py
hdx_cli/cli_interface/common/migration/resource_adapters.py
hdx_cli/cli_interface/common/migration/resource_migrations.py
hdx_cli/cli_interface/common/misc_operations.py
hdx_cli/cli_interface/common/rest_operations.py
hdx_cli/cli_interface/common/undecorated_click_commands.py
hdx_cli/cli_interface/credential/__init__.py
hdx_cli/cli_interface/credential/commands.py
hdx_cli/cli_interface/defaults/__init__.py
hdx_cli/cli_interface/defaults/commands.py
hdx_cli/cli_interface/dictionary/commands.py
hdx_cli/cli_interface/dictionary/operations.py
hdx_cli/cli_interface/docs/commands.py
hdx_cli/cli_interface/docs/config.py
hdx_cli/cli_interface/function/commands.py
hdxcli-1.0.83.dist-info/LICENSE
hdxcli-1.0.83.dist-info/METADATA
hdxcli-1.0.83.dist-info/WHEEL
hdxcli-1.0.83.dist-info/entry_points.txt
hdxcli-1.0.83.dist-info/RECORD
