Metadata-Version: 2.3
Name: hdxcli
Version: 1.0.83
Summary: Hydrolix command line utility to do CRUD operations on projects, tables, transforms and other resources in Hydrolix clusters
License: Apache-2.0
Keywords: database,bigdata,hydrolix
Author: German Diago Gomez
Author-email: german@hydrolix.io
Maintainer: Agustin Actis
Maintainer-email: agustin@hydrolix.io
Requires-Python: >=3.10,<4.0
Classifier: Development Status :: 3 - Alpha
Classifier: License :: OSI Approved :: Apache Software License
Classifier: Programming Language :: Python :: 3
Classifier: Programming Language :: Python :: 3.10
Classifier: Programming Language :: Python :: 3.11
Classifier: Programming Language :: Python :: 3.12
Classifier: Programming Language :: Python :: 3.13
Classifier: Topic :: Database
Classifier: Topic :: Database :: Front-Ends
Requires-Dist: click (>=8.1.3,<9.0.0)
Requires-Dist: inflect (>=7.5.0,<8.0.0)
Requires-Dist: inquirerpy (>=0.3.4,<0.4.0)
Requires-Dist: pydantic (>=2.5.3,<3.0.0)
Requires-Dist: pyjwt (>=2.10.1,<3.0.0)
Requires-Dist: requests (>=2.28.1,<3.0.0)
Requires-Dist: sqlglot (>=10.5.10,<11.0.0)
Requires-Dist: toml (>=0.10.2,<0.11.0)
Requires-Dist: tqdm (>=4.66.4,<5.0.0)
Requires-Dist: trogon (>=0.6.0,<0.7.0)
